{
    "status": true,
    "message": "success",
    "data": [
      {
        "id": "1",
       "title": " الأساليب الحديثة فى المرافعة واهم النقاط لنجاح القضية",
        "text": "نوفر لك الخدمات المميزة الكثيرة , خدمات خاصة بالمحامين والمؤسستات وخدمات خاصة بالعملاء انظر بالأسفل لتتعرف عليها",
        "image": "https://i.ibb.co/XD8zb7d/card2.jpg",
        "location": "الرياض, السعودية",
        "cost":"200 ر.س"
      },
      {
        "id": "2",
       "title": " الأساليب الحديثة فى المرافعة واهم النقاط لنجاح القضية",
        "text": "نوفر لك الخدمات المميزة الكثيرة , خدمات خاصة بالمحامين والمؤسستات وخدمات خاصة بالعملاء انظر بالأسفل لتتعرف عليها",
        "image": "https://i.ibb.co/XD8zb7d/card2.jpg",
        "location": "الرياض, السعودية",
        "cost":"200 ر.س"
      },
      {
        "id": "3",
       "title": " الأساليب الحديثة فى المرافعة واهم النقاط لنجاح القضية",
        "text": "نوفر لك الخدمات المميزة الكثيرة , خدمات خاصة بالمحامين والمؤسستات وخدمات خاصة بالعملاء انظر بالأسفل لتتعرف عليها",
        "image": "https://i.ibb.co/XD8zb7d/card2.jpg",
        "location": "الرياض, السعودية",
        "cost":"200 ر.س"
      },
      {
        "id": "4",
       "title": " الأساليب الحديثة فى المرافعة واهم النقاط لنجاح القضية",
        "text": "نوفر لك الخدمات المميزة الكثيرة , خدمات خاصة بالمحامين والمؤسستات وخدمات خاصة بالعملاء انظر بالأسفل لتتعرف عليها",
        "image": "https://i.ibb.co/XD8zb7d/card2.jpg",
        "location": "الرياض, السعودية",
        "cost":"200 ر.س"
      }
     
    ]
  }
  